build_tools/check_install_from_test_pypi.sh
build_tools/fail_on_missing_init_files.sh
build_tools/make_release.py
docs/Makefile
docs/source/conf.py
docs/source/index.rst
docs/source/releases.rst
docs/source/_static/custom_notebook.css
docs/source/_static/plotly_resize.js
docs/source/_static/images/changepoint_illustration.png
docs/source/_static/images/segment_anomaly_illustration.png
docs/source/_static/images/segmentation_illustration.png
docs/source/_templates/class.rst
docs/source/_templates/functions.rst
docs/source/api_reference/anomaly_detectors.rst
docs/source/api_reference/anomaly_scores.rst
docs/source/api_reference/base.rst
docs/source/api_reference/change_detectors.rst
docs/source/api_reference/change_scores.rst
docs/source/api_reference/compose.rst
docs/source/api_reference/costs.rst
docs/source/api_reference/datasets.rst
docs/source/api_reference/index.rst
docs/source/api_reference/penalties.rst
docs/source/api_reference/utils.rst
docs/source/developer_guide/code_style.rst
docs/source/developer_guide/contributing.rst
docs/source/developer_guide/for_maintainers.rst
docs/source/developer_guide/index.rst
docs/source/developer_guide/setup.rst
docs/source/user_guide/getting_started.ipynb
docs/source/user_guide/index.rst
docs/source/user_guide/anomaly_detection/index.rst
docs/source/user_guide/anomaly_detection/intro.ipynb
docs/source/user_guide/change_detection/index.rst
docs/source/user_guide/change_detection/intro.ipynb
docs/source/user_guide/concepts/detectors.ipynb
docs/source/user_guide/concepts/index.rst
docs/source/user_guide/concepts/interval_scores.ipynb
docs/source/user_guide/interval_scores/change_scores.ipynb
docs/source/user_guide/interval_scores/costs.ipynb
docs/source/user_guide/interval_scores/index.rst
docs/source/user_guide/interval_scores/local_anomaly_scores.ipynb
docs/source/user_guide/interval_scores/savings.ipynb
docs/source/user_guide/penalties/constant_penalties.ipynb
docs/source/user_guide/penalties/index.rst
skchange-0.14.3.dist-info/licenses/LICENSE
skchange-0.14.3.dist-info/METADATA
skchange-0.14.3.dist-info/WHEEL
skchange-0.14.3.dist-info/top_level.txt
skchange-0.14.3.dist-info/RECORD
