Metadata-Version: 2.4
Name: skchange
Version: 0.14.3
Summary: Sktime-compatible change and anomaly detection
Author-email: Martin Tveten <tveten@nr.no>
Maintainer-email: Martin Tveten <tveten@nr.no>, Johannes Voll Kolstø <jvkolsto@nr.no>
Project-URL: Homepage, https://skchange.readthedocs.io
Keywords: data-science,machine-learning,statistics,scikit-learn,time-series,change-detection,anomaly-detection
Classifier: Intended Audience :: Science/Research
Classifier: License :: OSI Approved :: BSD License
Classifier: Programming Language :: Python
Classifier: Topic :: Scientific/Engineering
Classifier: Operating System :: Microsoft :: Windows
Classifier: Operating System :: POSIX
Classifier: Operating System :: Unix
Classifier: Operating System :: MacOS
Classifier: Programming Language :: Python :: 3 :: Only
Classifier: Programming Language :: Python :: 3.10
Classifier: Programming Language :: Python :: 3.11
Classifier: Programming Language :: Python :: 3.12
Classifier: Programming Language :: Python :: 3.13
Requires-Python: <3.13.4,>=3.10
License-File: LICENSE
Requires-Dist: numpy>=1.21
Requires-Dist: pandas>=1.1
Requires-Dist: sktime>=0.35
Provides-Extra: numba
Requires-Dist: numba<0.62,>=0.61; extra == "numba"
Provides-Extra: all-extras
Requires-Dist: numba<0.62,>=0.61; extra == "all-extras"
Provides-Extra: test
Requires-Dist: pytest; extra == "test"
Requires-Dist: pytest-cov; extra == "test"
Requires-Dist: ruptures; extra == "test"
Provides-Extra: dev
Requires-Dist: pre-commit; extra == "dev"
Requires-Dist: pytest; extra == "dev"
Requires-Dist: pytest-cov; extra == "dev"
Requires-Dist: ipykernel; extra == "dev"
Requires-Dist: plotly; extra == "dev"
Requires-Dist: ruptures; extra == "dev"
Requires-Dist: nbformat>=4.2.0; extra == "dev"
Requires-Dist: scipy<2.0.0,>=1.14.1; extra == "dev"
Provides-Extra: docs
Requires-Dist: myst-parser; extra == "docs"
Requires-Dist: numpydoc; extra == "docs"
Requires-Dist: pypandoc; extra == "docs"
Requires-Dist: pydata-sphinx-theme; extra == "docs"
Requires-Dist: sphinx; extra == "docs"
Requires-Dist: sphinx-copybutton; extra == "docs"
Requires-Dist: sphinx-design; extra == "docs"
Requires-Dist: sphinx-gallery; extra == "docs"
Requires-Dist: sphinx-issues; extra == "docs"
Requires-Dist: tabulate; extra == "docs"
Requires-Dist: nbsphinx; extra == "docs"
Requires-Dist: nbstripout; extra == "docs"
Requires-Dist: ipykernel; extra == "docs"
Requires-Dist: nbformat>=4.2.0; extra == "docs"
Requires-Dist: plotly; extra == "docs"
Dynamic: license-file
